modeltree/__init__.py
modeltree/managers.py
modeltree/models.py
modeltree/query.py
modeltree/tree.py
modeltree/utils.py
modeltree/management/__init__.py
modeltree/management/commands/__init__.py
modeltree/management/commands/modeltree.py
modeltree/management/subcommands/__init__.py
modeltree/management/subcommands/preview.py
modeltree-2.0.1.dist-info/DESCRIPTION.rst
modeltree-2.0.1.dist-info/METADATA
modeltree-2.0.1.dist-info/RECORD
modeltree-2.0.1.dist-info/WHEEL
modeltree-2.0.1.dist-info/metadata.json
modeltree-2.0.1.dist-info/top_level.txt
