Metadata-Version: 2.0
Name: modeltree
Version: 2.0.1
Summary: Django ORM metaprogramming layer
Home-page: http://cbmi.github.com/modeltree/
Author: Byron Ruth
Author-email: b@devel.io
License: BSD
Keywords: Django meta ORM dynamic runtime
Platform: UNKNOWN
Classifier: Development Status :: 5 - Production/Stable
Classifier: License :: OSI Approved :: BSD License
Classifier: Programming Language :: Python :: 2.6
Classifier: Programming Language :: Python :: 2.7
Classifier: Framework :: Django
Classifier: Intended Audience :: Developers
Classifier: Intended Audience :: System Administrators
Classifier: Intended Audience :: Information Technology
Requires-Dist: django (<=1.11,>=1.8)
Requires-Dist: six (>=1.11)
